kaltts/__init__.py
kaltts/controller.py
kaltts/data_processing.py
kaltts/model.py
kaltts/synthesize.py
kaltts/train.py
kaltts/utils.py
kaltts/vocoder.py
kaltts-1.0.2012.dist-info/LICENSE
kaltts-1.0.2012.dist-info/METADATA
kaltts-1.0.2012.dist-info/WHEEL
kaltts-1.0.2012.dist-info/entry_points.txt
kaltts-1.0.2012.dist-info/top_level.txt
kaltts-1.0.2012.dist-info/RECORD
