Metadata-Version: 2.1
Name: kaltts
Version: 1.0.2012
Summary: Kal Text-to-Speech (TTS) Synthesis
Home-page: https://github.com/Odeneho-Calculus/KTTS_v1_model
Author: kalculusGuy
Author-email: calculus069@gmail.com
License: UNKNOWN
Project-URL: Bug Tracker, https://github.com/Odeneho-Calculus/KTTS_v1_model/issues
Project-URL: Documentation, https://github.com/Odeneho-Calculus/KTTS_v1_model#readme
Project-URL: Source Code, https://github.com/Odeneho-Calculus/KTTS_v1_model
Platform: UNKNOWN
Classifier: Programming Language :: Python :: 3
Classifier: License :: OSI Approved :: MIT License
Classifier: Operating System :: OS Independent
Classifier: Development Status :: 4 - Beta
Classifier: Intended Audience :: Developers
Classifier: Topic :: Multimedia :: Sound/Audio :: Speech
Requires-Python: >=3.6
License-File: LICENSE
Requires-Dist: pydub
Requires-Dist: requests
Requires-Dist: numpy
Requires-Dist: tensorflow
Requires-Dist: librosa
Requires-Dist: pyyaml
Requires-Dist: num2words
Requires-Dist: urllib3
